LibreGaming/LibreGaming.py
LibreGaming/LibreGamingQt.py
LibreGaming/__init__.py
LibreGaming/__main__.py
LibreGaming/distro_pkgs/Arch.py
LibreGaming/distro_pkgs/Common_Pkgs.py
LibreGaming/distro_pkgs/Fedora.py
LibreGaming/distro_pkgs/OpenSUSE.py
LibreGaming/distro_pkgs/Ubuntu.py
test/__init__.py
test/tests_libregaming.py
LibreGaming-0.2.4.2.dist-info/LICENSE
LibreGaming-0.2.4.2.dist-info/METADATA
LibreGaming-0.2.4.2.dist-info/WHEEL
LibreGaming-0.2.4.2.dist-info/entry_points.txt
LibreGaming-0.2.4.2.dist-info/top_level.txt
LibreGaming-0.2.4.2.dist-info/RECORD
