Metadata-Version: 2.1
Name: LibreGaming
Version: 0.2.4.2
Summary: Install Gaming Packages with ease
Home-page: https://github.com/Ahmed-Al-Balochi/LibreGaming.git
Author: Ahmed Al Balochi
License: GPL-3.0
Requires-Python: >3.7
License-File: LICENSE
Requires-Dist: argparse
Requires-Dist: requests
Requires-Dist: wget
